pot/__init__.py
pot/drama.py
pot/server.py
pot/story.py
pot/types.py
pot/world.py
pot/css/pot.css
pot/dlg/__init__.py
pot/dlg/freda/12_intervention.rst
pot/dlg/freda/14_introduction.rst
pot/dlg/freda/__init__.py
pot/dlg/gerod/12_intervention.rst
pot/dlg/gerod/__init__.py
pot/dlg/iysla/12_intervention.rst
pot/dlg/iysla/14_introduction.rst
pot/dlg/iysla/__init__.py
pot/dlg/niall/12_intervention.rst
pot/dlg/niall/14_introduction.rst
pot/dlg/niall/__init__.py
pot/dlg/odric/00_introduction.rst
pot/dlg/odric/12_intervention.rst
pot/dlg/odric/13_exploration.rst
pot/dlg/odric/__init__.py
pot/img/beggars_ash.png
pot/img/bridge_street.png
pot/img/butchers_row.png
pot/img/cutthroat_lane.png
pot/img/dingwood.png
pot/img/gardens.png
pot/img/icehouse_jam-logo.png
pot/img/inventory.png
pot/img/market.png
pot/img/market_house.png
pot/img/mordiford_quay.png
pot/img/north_gate.png
pot/img/orchard.png
pot/img/ross_road.png
pot/img/south_end.png
pot/img/tavern.png
pot/img/top_cross.png
pot/img/tower_street.png
pot/img/tower_street_e.png
pot/img/tower_street_w.png
pot/img/tower_wall.png
pot/img/woodshed.png
pot/img/yard.png
pot/mp3/crow_call-3s.mp3
pot/mp3/pot_arp_slow.mp3
pot/test/__init__.py
pot/test/test_drama.py
pot/test/test_story.py
pot/test/test_world.py
pity_of_thieves-0.9.0.dist-info/LICENSE
pity_of_thieves-0.9.0.dist-info/METADATA
pity_of_thieves-0.9.0.dist-info/WHEEL
pity_of_thieves-0.9.0.dist-info/entry_points.txt
pity_of_thieves-0.9.0.dist-info/top_level.txt
pity_of_thieves-0.9.0.dist-info/zip-safe
pity_of_thieves-0.9.0.dist-info/RECORD
