Metadata-Version: 2.1
Name: pity-of-thieves
Version: 0.9.0
Summary: A simple text adventure.
Home-page: https://github.com/tundish/pity_of_thieves
Author: D E Haynes
Author-email: tundish@gigeconomy.org.uk
License: UNKNOWN
Platform: UNKNOWN
Classifier: Operating System :: OS Independent
Classifier: Programming Language :: Python :: 3.7
Classifier: Programming Language :: Python :: 3.8
Classifier: Programming Language :: Python :: 3.9
Classifier: License :: OSI Approved :: GNU Affero General Public License v3 or later (AGPLv3+)
License-File: LICENSE
Requires-Dist: aiohttp (>=3.8.1)
Requires-Dist: balladeer (==0.24.0)
Provides-Extra: dev
Requires-Dist: flake8 (>=3.7.0) ; extra == 'dev'
Requires-Dist: wheel (>=0.33.0) ; extra == 'dev'
